think/__init__.py
think/ai.py
think/parser.py
think/prompt.py
think/llm/__init__.py
think/llm/anthropic.py
think/llm/base.py
think/llm/bedrock.py
think/llm/chat.py
think/llm/google.py
think/llm/groq.py
think/llm/hf.py
think/llm/ollama.py
think/llm/openai.py
think/llm/tool.py
think/rag/base.py
think/rag/chroma_rag.py
think/rag/eval.py
think/rag/pinecone_rag.py
think/rag/rag.py
think/rag/txtai_rag.py
think_llm-0.0.9.dist-info/METADATA
think_llm-0.0.9.dist-info/WHEEL
think_llm-0.0.9.dist-info/licenses/LICENSE
think_llm-0.0.9.dist-info/RECORD
