Metadata-Version: 2.4
Name: think-llm
Version: 0.0.9
Summary: Create programs that think, using LLMs.
Author-email: Senko Rasic <senko@senko.net>
License: MIT
License-File: LICENSE
Keywords: ai,llm,rag
Requires-Python: >=3.10
Requires-Dist: httpx>=0.27.2
Requires-Dist: jinja2>=3.1.2
Requires-Dist: pydantic>=2.9.2
Provides-Extra: all
Requires-Dist: aioboto3>=13.2.0; extra == 'all'
Requires-Dist: anthropic>=0.37.1; extra == 'all'
Requires-Dist: chromadb>=0.6.2; extra == 'all'
Requires-Dist: google-generativeai>=0.8.3; extra == 'all'
Requires-Dist: groq>=0.12.0; extra == 'all'
Requires-Dist: ollama>=0.3.3; extra == 'all'
Requires-Dist: openai>=1.53.0; extra == 'all'
Requires-Dist: pinecone-client>=4.1.2; extra == 'all'
Requires-Dist: pinecone>=5.4.2; extra == 'all'
Requires-Dist: txtai>=8.1.0; extra == 'all'
Provides-Extra: anthropic
Requires-Dist: anthropic>=0.37.1; extra == 'anthropic'
Provides-Extra: bedrock
Requires-Dist: aioboto3>=13.2.0; extra == 'bedrock'
Provides-Extra: chromadb
Requires-Dist: chromadb>=0.6.2; extra == 'chromadb'
Provides-Extra: gemini
Requires-Dist: google-generativeai>=0.8.3; extra == 'gemini'
Provides-Extra: groq
Requires-Dist: groq>=0.12.0; extra == 'groq'
Provides-Extra: ollama
Requires-Dist: ollama>=0.3.3; extra == 'ollama'
Provides-Extra: openai
Requires-Dist: openai>=1.53.0; extra == 'openai'
Provides-Extra: pinecone
Requires-Dist: pinecone>=5.4.2; extra == 'pinecone'
Provides-Extra: txtai
Requires-Dist: txtai>=8.1.0; extra == 'txtai'
